portend.py
portend-3.2.0.dist-info/LICENSE
portend-3.2.0.dist-info/METADATA
portend-3.2.0.dist-info/WHEEL
portend-3.2.0.dist-info/top_level.txt
portend-3.2.0.dist-info/RECORD
