Metadata-Version: 2.1
Name: portend
Version: 3.2.0
Summary: TCP port monitoring and discovery
Home-page: https://github.com/jaraco/portend
Author: Jason R. Coombs
Author-email: jaraco@jaraco.com
Classifier: Development Status :: 5 - Production/Stable
Classifier: Intended Audience :: Developers
Classifier: License :: OSI Approved :: MIT License
Classifier: Programming Language :: Python :: 3
Classifier: Programming Language :: Python :: 3 :: Only
Requires-Python: >=3.8
Provides-Extra: testing
Provides-Extra: docs
License-File: LICENSE
